{
  "$schema": "https://json-schema.org/draft/2020-12/schema",
  "$id": "https://corpusos.com/schemas/vector/vector.namespace.delete.success.json",
  "title": "vector.delete_namespace result", 
  "description": "Namespace deletion result per protocol ยง14.10.",
  "type": "object",
  "additionalProperties": false,
  "properties": {
    "success": { "type": "boolean" },
    "namespace": { "type": "string", "maxLength": 256 },
    "details": {
      "type": "object", 
      "additionalProperties": true
    },
    "vector_count": { "type": "integer", "minimum": 0 }
  },
  "required": ["success", "namespace", "details"]
}